crop_video/__init__.py
crop_video/main.py
crop_video-0.0.1.dist-info/LICENSE
crop_video-0.0.1.dist-info/METADATA
crop_video-0.0.1.dist-info/WHEEL
crop_video-0.0.1.dist-info/entry_points.txt
crop_video-0.0.1.dist-info/top_level.txt
crop_video-0.0.1.dist-info/RECORD
