Metadata-Version: 2.1
Name: crop-video
Version: 0.0.1
Summary: Cut video based on moviepy
Home-page: https://github.com/SWHL/CutVideo
Author: SWHL
Author-email: liekkaskono@163.com
License: MIT
Keywords: moviepy,crop_video
Platform: Any
Classifier: Programming Language :: Python :: 3.6
Classifier: Programming Language :: Python :: 3.7
Classifier: Programming Language :: Python :: 3.8
Classifier: Programming Language :: Python :: 3.9
Classifier: Programming Language :: Python :: 3.10
Classifier: Programming Language :: Python :: 3.11
Requires-Python: >=3.6,<3.12
Requires-Dist: moviepy ==1.0.3
